himon/__init__.py
himon/exceptions.py
himon/league_of_comic_geeks.py
himon/sqlite_cache.py
himon/schemas/__init__.py
himon/schemas/_validators.py
himon/schemas/comic.py
himon/schemas/generic.py
himon/schemas/series.py
himon-0.8.0.dist-info/METADATA
himon-0.8.0.dist-info/WHEEL
himon-0.8.0.dist-info/licenses/LICENSE
himon-0.8.0.dist-info/RECORD
