Metadata-Version: 2.4
Name: Himon
Version: 0.8.0
Summary: A Python wrapper for League of Comic Geeks.
Project-URL: Documentation, https://himon.readthedocs.io/en/latest/
Project-URL: Homepage, https://pypi.org/project/Himon
Project-URL: Issues, https://github.com/Buried-In-Code/Himon/issues
Project-URL: Source, https://github.com/Buried-In-Code/Himon
Author-email: BuriedInCode <BuriedInCode@tuta.io>
Maintainer-email: BuriedInCode <BuriedInCode@tuta.io>
License-Expression: MIT
License-File: LICENSE
Keywords: comic,comics,metadata
Classifier: Development Status :: 4 - Beta
Classifier: Environment :: Console
Classifier: Framework :: Pydantic :: 2
Classifier: Intended Audience :: Developers
Classifier: Natural Language :: English
Classifier: Operating System :: OS Independent
Classifier: Programming Language :: Python
Classifier: Programming Language :: Python :: 3.10
Classifier: Programming Language :: Python :: 3.11
Classifier: Programming Language :: Python :: 3.12
Classifier: Programming Language :: Python :: 3.13
Classifier: Programming Language :: Python :: 3.14
Classifier: Topic :: Internet
Classifier: Typing :: Typed
Requires-Python: >=3.10
Requires-Dist: httpx>=0.28.0
Requires-Dist: pydantic>=2.12.0
Requires-Dist: pyrate-limiter>=3.9.0
